LICENSE.txt
NOTICE.txt
README.md
pyproject.toml
setup.py
src/srrcomp/__init__.py
src/srrcomp/srrcomp.py
src/srrcomp.egg-info/PKG-INFO
src/srrcomp.egg-info/SOURCES.txt
src/srrcomp.egg-info/dependency_links.txt
src/srrcomp.egg-info/requires.txt
src/srrcomp.egg-info/top_level.txt
src/srrcomp/eden_utils/csrc/cuda_hadamard.h
src/srrcomp/eden_utils/csrc/cuda_packing.h
src/srrcomp/eden_utils/csrc/defs.h