Metadata-Version: 2.1
Name: srrcomp
Version: 0.1.3
Summary: Structured random rotation (srr) based compression tools
Home-page: https://github.com/shayvar/structured-random-rotation-based-compression
Author: Shay Vargaftik and Yaniv Ben-Itzhak
Author-email: shayv@vmware.com, ybenitzhak@vmware.com
License: BSD-3-Clause
License-File: LICENSE.txt
License-File: NOTICE.txt
Requires-Dist: torch
Requires-Dist: numpy
